sbiRandM/__init__.py
sbiRandM/check_stoichometry.py
sbiRandM/complex_build.py
sbiRandM/data.py
sbiRandM/exceptions.py
sbiRandM/interaction_module.py
sbiRandM/mainModeller.py
sbiRandM/mainSuperimp.py
sbiRandM/mainWindow.py
sbiRandM/modeller_comparison.py
sbiRandM/models.py
sbiRandM/pairwise_generator.py
sbiRandM/pdb_to_fasta.py
sbiRandM/superimp.py
sbiRandM-2.1.0.dist-info/LICENSE
sbiRandM-2.1.0.dist-info/METADATA
sbiRandM-2.1.0.dist-info/WHEEL
sbiRandM-2.1.0.dist-info/top_level.txt
sbiRandM-2.1.0.dist-info/RECORD
