Metadata-Version: 2.1
Name: sbiRandM
Version: 2.1.0
Summary: Protein-DNA Complex builder
Home-page: https://github.com/RMolina93/Structural_Project
Author: Ruben-And-Miguel
Author-email: ruben.molina-fernandez@upf.edu
License: UNKNOWN
Platform: UNKNOWN
Classifier: Programming Language :: Python :: 3
Classifier: License :: OSI Approved :: MIT License
Classifier: Operating System :: OS Independent
Requires-Python: >=3.6
Requires-Dist: biopython
